<odoo>
<!--    <record id="purchase_order_tree_view_freightbox" model="ir.ui.view">-->
<!--        <field name="name">purchase.order.tree.freightbox</field>-->
<!--        <field name="model">purchase.order</field>-->
<!--        <field name="priority">1</field>-->
<!--        <field name="arch" type="xml">-->
<!--            <tree string="Purchase" sample="1" multi_edit="1" decoration-bf="state == 'draft'"-->
<!--                      decoration-success="state == 'purchase'" decoration-info="state == 'sent'">-->
<!--                <field name="po_inquiry_id" />-->
<!--                <field name="name" string="Reference"/>-->
<!--                <field name="partner_id" string="Vendor"/>-->
<!--                <field name="company_id" string="Company"/>-->
<!--                <field name="date_planned" string="Receipt Date"/>-->
<!--                <field name="user_id" string="Purchase Representative"/>-->
<!--                <field name="amount_total" string="Total" widget='monetary'-->
<!--                           options="{'currency_field': 'currency_id', 'field_digits': True}"/>-->
<!--                <field name="state" string="Status" widget="badge" decoration-success="state == 'purchase'" decoration-bf="state == 'draft'" decoration-info="state == 'sent'"/>-->
<!--                <field name="currency_id" invisible="1"/>-->
<!--            </tree>-->
<!--        </field>-->
<!--    </record>-->

<!--    <record model="ir.actions.server" id="po_by_emial">-->
<!--        <field name="name">Send PO by Email</field>-->
<!--        <field name="model_id" ref="model_purchase_order"/>-->
<!--        <field name="binding_model_id" ref="model_purchase_order"/>-->
<!--        <field name="state">code</field>-->
<!--        <field name="code">-->
<!--            action = records.action_rfq_send()-->
<!--        </field>-->
<!--    </record>-->

    <record id="purchase_order_form" model="ir.ui.view">
            <field name="name">FreightBox PO</field>
            <field name="model">purchase.order</field>
            <field name="mode">primary</field>
            <field name="inherit_id" ref="base_freightbox.purchase_order_form"/>
            <field name="arch" type="xml">
                <xpath expr="/form/sheet/notebook/page/field[@name='order_line']/tree/field[@name='taxes_id']" position="after">
                    <field name="today_exchange_rate" attrs="{'column_invisible': [('parent.is_freight_box_po', '=', False)]}"/>
                    <field name="exchange_from_to_currency" attrs="{'column_invisible': [('parent.is_freight_box_po', '=', False)]}"/>
                </xpath>
                <xpath expr="//button[@name='action_rfq_send']" position="replace">
                    <button name="action_shipment_quote"
                        string="Create Shipment Quote" type="object"
                        attrs="{'invisible': ['|', ('sq_count','&gt;','0'), ('is_freight_box_po', '=', False)]}"
                        class="oe_highlight"/>
                </xpath>
                <xpath expr="//button[@name='button_confirm']" position="replace">
                    <button name="button_confirm" string="confirm order" 
                    type="object" class="oe_highlight"
                    attrs="{'invisible': [('state','=','purchase')]}"/>
                    <!-- attrs="{'invisible': ['|', ('state','!=','purchase'), ('is_freight_box_po', '=', False)]}" -->
                </xpath>
                <xpath expr="//button[@id='draft_confirm']" position="replace">
                    <button name="%(freightbox.act_po_correct_wiz)d" string="Correct"
                            type="action"  attrs="{'invisible': ['|','|', ('job_id', '!=', False), ('po_inquiry_status','=','under_correction'),('is_freight_box_po', '=', False)]}"
                            class="oe_highlight"/>
                    <button name="button_confirm_correction" string="Confirm Correction" attrs="{'invisible': ['|',('po_inquiry_status','!=','under_correction'),('is_freight_box_po', '=', False)]}"
                            confirm="Are you sure, you want to confirm this correction?"
                            type="object" class="oe_highlight"/>
                </xpath>
                <xpath expr="//div[hasclass('oe_button_box')]" position="inside">
                    <button name="action_get_sq"
                            type="object" attrs="{'invisible': ['|', ('sq_count','&lt;','1'), ('is_freight_box_po', '=', False)]}"
                            class="oe_stat_button"
                            icon="fa-pencil-square-o"
                            help="Shows the Shipment Quote,related to this Purchase order">
                            <field name="sq_count" widget="statinfo" string="Shipment Quote"/>
                        </button>
                </xpath>
                <xpath expr="//field[@name='priority']" position="replace">
                    <field name="priority" invisible="1"/>
                </xpath>
<!--                <xpath expr="//field[@name='partner_id']" position="replace">-->
<!--                <field name="rfq_id" options="{'no_create': 1, 'no_edit': 1,}"-->
<!--                                domain="[('state', '=', 'approved'), ('is_po_created', '=', False), ('is_shipment_quote_created', '=', False)]"-->
<!--                                attrs="{'readonly': [('state','!=','draft')], 'invisible': [('is_freight_box_po', '=', False)]}"/>-->
<!--                    <field name="partner_id" domain="[('supplier_rank', '>', 0)]"/>-->
<!--                </xpath>-->
                <xpath expr="//field[@name='origin']" position="after">
                    <field name="correct_reason_bool" invisible="1"/>
<!--                     <field name="is_freight_box_po" invisible="1"/>-->
<!--                    <field name="po_inquiry_status" readonly="1" attrs="{'invisible': [('is_freight_box_po', '=', False)]}"/>-->
                    <field name="invoice_id" readonly="1" attrs="{'invisible': [('is_freight_box_po', '=', False)]}"/>
                    <field name="vendor_bill_id" readonly="1" attrs="{'invisible': [('is_freight_box_po', '=', False)]}"/>
                </xpath>
                <!--<xpath expr="//notebook" position="before">
                    <group name="p_detail" string="Party details" attrs="{'invisible': ['|', ('total_collect_charges', '=', 0), ('is_freight_box_po', '=', False)],  'required':['|', ('total_collect_charges', '!=', 0), ('is_freight_box_po', '=', True)]}">
                        <group>
                            <field name="party_name_id" widget="res_partner_many2one" attrs="{
                            'invisible': ['|',('total_collect_charges', '=', 0), ('is_freight_box_po', '=', False)],
                            'required':[('total_collect_charges', '!=', 0), ('is_freight_box_po', '=', True)]}"/>
                            <field name="tax_reference_1" attrs="{
                                'invisible': ['|',('total_collect_charges', '=', 0), ('is_freight_box_po', '=', False)],
                                'required':[('total_collect_charges', '!=', 0), ('is_freight_box_po', '=', True)]}"/>
                            <field name="street" attrs="{
                                'invisible': ['|',('total_collect_charges', '=', 0), ('is_freight_box_po', '=', False)],
                                'required':[('total_collect_charges', '!=', 0), ('is_freight_box_po', '=', True)]}"/>
                            <field name="street_number" attrs="{'invisible': ['|',('total_collect_charges', '=', 0), ('is_freight_box_po', '=', False)],  'required':[('total_collect_charges', '!=', 0), ('is_freight_box_po', '=', True)]}"/>
                            <field name="floor" attrs="{'invisible': ['|',('total_collect_charges', '=', 0), ('is_freight_box_po', '=', False)], 'required':[ ('total_collect_charges', '!=', 0), ('is_freight_box_po', '=', True)]}"/>
                        </group>
                        <group>
                            <field name="post_code" attrs="{'invisible': ['|',('total_collect_charges', '=', 0), ('is_freight_box_po', '=', False)],  'required':[ ('total_collect_charges', '!=', 0), ('is_freight_box_po', '=', True)]}"/>
                            <field name="city" attrs="{'invisible': ['|',('total_collect_charges', '=', 0), ('is_freight_box_po', '=', False)],  'required':[('total_collect_charges', '!=', 0), ('is_freight_box_po', '=', True)]}"/>
                            <field name="state_region" attrs="{'invisible': ['|',('total_collect_charges', '=', 0), ('is_freight_box_po', '=', False)],  'required':[ ('total_collect_charges', '!=', 0), ('is_freight_box_po', '=', True)]}" />
                            <field name="country" attrs="{'invisible': ['|',('total_collect_charges', '=', 0), ('is_freight_box_po', '=', False)],  'required':[ ('total_collect_charges', '!=', 0), ('is_freight_box_po', '=', True)]}"/>
                        </group>
                    </group>
                </xpath>-->
                <xpath expr="//page[@name='products']" position="before" >
                   <!-- <page name='cargo_description' string="Cargo "  attrs="{'invisible': [('is_freight_box_po', '=', False)]}">
                        <group invisible="1">
                            <group>
                                <field name="job_id" invisible="1" readonly="1"/>
                            </group>
                        </group>
                        <group >
                            <group >
                                <field name="cargo_name" attrs="{'readonly': [('po_inquiry_status', 'not in', ('under_correction'))]}" force_save="1"/>
                                <field name="quantity" attrs="{'readonly': [('po_inquiry_status', 'not in', ('under_correction'))]}" force_save="1"/>
                                <field name="weight" attrs="{'readonly': [('po_inquiry_status', 'not in', ('under_correction'))]}" force_save="1"/>
                                <field name="weight_uom" attrs="{'readonly': [('po_inquiry_status', 'not in', ('under_correction'))]}" force_save="1"/>
                                <field name="volume" attrs="{'readonly': [('po_inquiry_status', 'not in', ('under_correction'))]}" force_save="1"/>
                                <field name="volume_uom" attrs="{'readonly': [('po_inquiry_status', 'not in', ('under_correction'))]}" force_save="1"/>
                                <field name="move_type" attrs="{'readonly': [('po_inquiry_status', 'not in', ('under_correction'))]}" force_save="1"/>
                                <field name="incoterm_id" attrs="{'readonly': [('po_inquiry_status', 'not in', ('under_correction'))]}" force_save="1"/>
                                <field name="place_of_origin" attrs="{'readonly': [('po_inquiry_status', 'not in', ('under_correction'))]}" force_save="1"/>
                                <field name="final_port_of_destination" attrs="{'readonly': [('po_inquiry_status', 'not in', ('under_correction'))]}" force_save="1"/>
                                <field name="point_of_stuffing" attrs="{'readonly': [('po_inquiry_status', 'not in', ('under_correction'))]}" force_save="1"/>
                                <field name="point_of_destuffing" attrs="{'readonly': [('po_inquiry_status', 'not in', ('under_correction'))]}" force_save="1"/>
                            </group>
                            <group>
                                <field name="no_of_expected_container" attrs="{'readonly': [('po_inquiry_status', 'not in', ('under_correction'))]}" force_save="1"/>
                                <field name="container_type" attrs="{'readonly': [('po_inquiry_status', 'not in', ('under_correction'))]}" force_save="1"/>
                                <field name="valid_from" attrs="{'readonly': [('po_inquiry_status', 'not in', ('under_correction'))]}" force_save="1"/>
                                <field name="valid_to" attrs="{'readonly': [('po_inquiry_status', 'not in', ('under_correction'))]}" force_save="1"/>
                                <field name="expected_date_of_shipment" attrs="{'readonly': [('po_inquiry_status', 'not in', ('under_correction'))]}" force_save="1"/>
                                <field name="shipment_terms" attrs="{'readonly': [('po_inquiry_status', 'not in', ('under_correction'))]}" force_save="1"/>
                                <field name="remarks" attrs="{'readonly': [('po_inquiry_status', 'not in', ('under_correction'))]}" force_save="1"/>
                                <field name="po_inquiry_id" invisible="1"/>
                                <field name="active" invisible="1"/>
                                <field name="booking_user_id" readonly="1"/>
                                <field name="delivery_type_id"/>

                            </group>
                        </group>
                    </page>
                    <page name="cargo_plus" string="Cargo Plus">
                        <separator string="Additional Cargo Details"/>
                        <field name="cargo_plus_ids"/>
                    </page>
                    <page name='rate' string="Rate" attrs="{'invisible': [('is_freight_box_po', '=', False)]}" >
                        <separator string="Charges"/>
                        <field name="charges_line" attrs="{'readonly': [('po_inquiry_status', 'not in', ('under_correction'))]}">
                            <tree string="Charges" editable="bottom">
                                <field name="charges_id" required="1"/>
                                <field name="charge_line_insert_update" invisible="1"/>
                                <field name="charges_type" readonly="1" force_save="1"/>
                                <field name="container_type" readonly="1" force_save="1"/>
                                <field name="charge_load_bool" invisible="1"/>
                                <field name="is_loaded_for_rfq" invisible="1"/>
                                <field name="units" readonly="1" force_save="1"/>
                                <field name="unit_price" required="1" widget='monetary'
                                            options="{'currency_field': 'currency_id', 'field_digits': True}"/>
                                <field name="base_currency_id" invisible="1"/>
                                <field name="taxes_id" widget="many2many_tags" style="width: 150px !important"/>
                                <field name="currency_id" required="1" string="From CRR"/>
                                <field name="tax_amt" readonly="1" force_save="1" widget='monetary'
                                       options="{'currency_field': 'currency_id', 'field_digits': True}"/>
                                <field name="final_amount" widget='monetary' string="Total Cost Tax Included "
                                    options="{'currency_field': 'to_currency_id', 'field_digits': True}"/>
                                <field name="to_currency_id" string="To CRR" required="1"/>
                                <field name="today_exchange_rate"/>
                                <field name="prepaid" force_save="1"/>
                                <field name="collect" force_save="1"/>
                                <field name="comment"/>
                                <field name="company_currency_total" widget='monetary' optional="hide"
                                    options="{'currency_field': 'base_currency_id', 'field_digits': True}"/>
                            </tree>
                        </field>
                            <group>
                             <group>
                                        <label for="total_prepaid_charges"/>
                                    <div name="amount_div" class="o_row">
                                        <field name="total_prepaid_charges" widget='monetary'
                                               options="{'currency_field': 'currency_id', 'field_digits': True}"/>
                                        <field name="currency_id"
                                               options="{'no_create': True, 'no_open': True}"
                                               />
                                    </div>
                                    </group>
                                    <group>

                                       <label for="total_collect_charges"/>
                                    <div name="amount_div" class="o_row">
                                        <field name="total_collect_charges" widget='monetary'
                                               options="{'currency_field': 'currency_id', 'field_digits': True}"/>
                                        <field name="currency_id"
                                               options="{'no_create': True, 'no_open': True}"
                                               />
                                    </div>
                                    </group>
                                </group>


                                <separator/>
                        <group>
                            <group>
                                <label for="total_freight_charge"/>
                                <div name="amount_div" class="o_row">
                                    <field name="total_freight_charge" widget='monetary'
                                        options="{'currency_field': 'currency_id', 'field_digits': True}"/>
                                    <field name="currency_id"
                                        options="{'no_create': True, 'no_open': True}"
                                        />
                                </div>
                                <label for="total_destination_charge"/>
                                <div name="amount_div" class="o_row">
                                    <field name="total_destination_charge" widget='monetary'
                                        options="{'currency_field': 'currency_id', 'field_digits': True}"/>
                                    <field name="currency_id"
                                        options="{'no_create': True, 'no_open': True}"
                                        />
                                </div>
                            </group>
                            <group>
                                <label for="total_origin_charge"/>
                                <div name="amount_div" class="o_row">
                                    <field name="total_origin_charge" widget='monetary'
                                        options="{'currency_field': 'currency_id', 'field_digits': True}"/>
                                    <field name="currency_id"
                                        options="{'no_create': True, 'no_open': True}"
                                        />
                                </div>
                                <label for="total_charge"/>
                                <div name="amount_div" class="o_row">
                                    <field name="total_charge" widget='monetary'
                                        options="{'currency_field': 'currency_id', 'field_digits': True}"/>
                                    <field name="currency_id"
                                        options="{'no_create': True, 'no_open': True}"
                                        />
                                </div>
                            </group>
                        </group>

                    </page>-->
                    <page name="correction" string="Correction Reason"
                            attrs="{'invisible': [('correct_reason_bool','!=', True)]}">
                            <group colspan="2" col="2">
                                <field name="correct_reason" readonly="1"/>
                            </group>
                    </page>
                </xpath>
                <xpath expr="//notebook" position="inside" >
                    <page string="Video Tutorial" attrs="{'invisible': [('is_freight_box_po', '=', False)]}">
                        <button name="open_po_tutorial_video_new_tab" type="object" class="btn-primary" string="Open Full Tutorial Video in New Tab"/>
                        <div class="app_settings_block" string="PO Tutorial">
                            <div class="row mt16 o_settings_container" name="qualification_setting_container">
                                <div controls="true"  class="embed-responsive embed-responsive-16by9">
                                    <iframe width="1080px" height="720px" id="purchase_order_tutorial_video"  src=""></iframe>
                                </div>
                            </div>
                        </div>
                    </page>
                </xpath>
                <div class="oe_chatter">
                    <field name="message_follower_ids"/>
                    <field name="activity_ids"/>
                    <field name="message_ids"/>
                </div>
            </field>
    </record>

<!--    <record id="action_fb_purchase_management" model="ir.actions.act_window">-->
<!--            <field name="name">Purchase</field>-->
<!--            <field name="res_model">purchase.order</field>-->
<!--            <field name="view_mode">tree,form</field>-->
<!--            <field name="context">{'default_is_freight_box_po': True}</field>-->
<!--            <field name="domain">[('is_freight_box_po', '=', True)]</field>-->
<!--            <field name="view_ids" eval="[(5, 0, 0),-->
<!--                (0, 0, {'view_mode': 'tree', 'view_id': ref('purchase_order_tree_view_freightbox')}),-->
<!--                (0, 0, {'view_mode': 'form', 'view_id': ref('purchase_order_form')})]"-->
<!--            />-->
<!--            <field name="help" type="html">-->
<!--                <p>-->
<!--                    To create employees timesheet.-->
<!--                </p>-->
<!--            </field>-->
<!--    </record>-->
</odoo>
